tppc/__init__.py
tppc/__main__.py
tppc/tppc.py
tppc-5.1.0.dist-info/METADATA
tppc-5.1.0.dist-info/WHEEL
tppc-5.1.0.dist-info/entry_points.txt
tppc-5.1.0.dist-info/top_level.txt
tppc-5.1.0.dist-info/RECORD
