Metadata-Version: 2.1
Name: tppc
Version: 5.1.0
Summary: T++ Quantum Execution Framework
Home-page: https://github.com/YOUR_GITHUB_USERNAME/tppc
Author: Sean Tichenor
License: MIT
Classifier: Programming Language :: Python :: 3
Classifier: License :: OSI Approved :: MIT License
Classifier: Operating System :: POSIX :: Linux
Requires-Dist: pyyaml
